{"3d99a7":["PA34","Mewa PZL M-20","Pzl-mielec"],"3d9f0b":["MC10","Cri-Cri MC-15","Colomban"],"3d99c2":["P68","P.68B Victor","Partenavia"],"3d9042":["PA34","PA-34 220T Seneca III","Piper"],"3d98a5":["PA44","PA-44 180T Turbo Seminole","Piper"],"3d9721":["PA34","PA-34 220T Seneca III","Piper"],"3d98e2":["PA44","PA-44 180 Seminole","Piper"],"3d90b7":["DA42","Twin Star DA42","Diamond Aircraft"],"3d9635":["DA42","Twin Star DA42 NG","Diamond Aircraft"],"3d9cb8":["P68","P.68B Victor","Partenavia"],"3d97b8":["P68","Partenavia P.68C TC","Partenavia"],"3d9060":["PA34","PA-34 220T Seneca III","Piper"],"3d9ce6":["DA42","",""],"3d947f":["PA44","PA-44 180 Seminole","Piper"],"3d9142":["P68","P.68C TC","Partenavia"],"3d997d":["PA34","PA-34 200T Seneca II","Piper"],"3d92d8":["PA34","PA-34 200T Seneca II","Piper"],"3d99da":["BE95","Travel Air 95","Beech"],"3d9376":["PA34","PA-34 220T Seneca III","Piper"],"3d9a51":["P68","P.68B Victor","Partenavia"],"3d98fa":["P68","P.68C Victor","Partenavia"],"3d9cba":["P68","P.68B Victor","Partenavia"],"3d9dd1":["PA34","PA-34 220T Seneca IV","Piper"],"3d9963":["PA34","PA-34 220T Seneca IV","Piper"],"3d92d4":["PA44","PA-44 180 Seminole","Piper"],"3d99ae":["P68","P.68B Victor","Partenavia"],"3d98ea":["PA34","",""],"3d9588":["P06T","P.2006T","Tecnam"],"3d9e6f":["P68","",""],"3d9912":["PA34","PA-34 220T Seneca V","Piper"],"3d900b":["PA34","PA-34 220T Seneca V","Piper"],"3d9889":["PA30","",""],"3d99bd":["PA34","Piper PA-34 220T Seneca V","Piper"],"3d9172":["PA34","PA-34 200T Seneca II","Piper"],"3d9a43":["P68","P.68B Victor","Partenavia"],"3d9692":["P06T","",""],"3d9e6c":["PA34","PA-34 220T Seneca III","Piper"],"3d9e49":["DA42","Diamond Aircraft Twin Star DA42 NG","Diamond Aircraft"],"3d97e1":["PA34","PA-34 200T Seneca II","Piper"],"3d99a9":["PA34","PA-34 200T Seneca II","Piper"],"3d99c5":["P68","P.68C TC","Partenavia"],"3d90b1":["PA44","PA-44 180T Turbo Seminole","Piper"],"3d9502":["MC10","Cri-Cri MC-12","Colomban"],"3d99c8":["P68","P.68C TC","Partenavia"],"3d925a":["DA42","",""],"3d997b":["PA34","PA-34 220T Seneca III","Piper"],"3d9b3e":["DA42","Twin Star DA42 NG","Diamond Aircraft"],"3d94c6":["MC10","Cri-Cri MC-15","Colomban"],"3d9feb":["P06T","P.2006T","Tecnam"],"3d993f":["PA30","PA-30 160 Twin Comanche B","Piper"],"3d9a64":["PA44","PA-44 180 Seminole","Piper"],"3d95f8":["BE95","Travel Air 95","Beech"],"3d9a89":["PA34","PA-34 200T Seneca II","Piper"],"3d9ef2":["PA34","PA-34 220T Seneca V","Piper"],"3d99a2":["PA34","PA-34 220T Seneca III","Piper"],"3d9557":["DA42","Twin Star DA42 NG","Diamond Aircraft"],"3d982b":["PA34","PA-34 220T Seneca IV","Piper"],"3d9942":["PA23","PA-23 Apache 150","Piper"],"3d9be1":["P06T","",""],"3d9f52":["PA34","PA-34 200 Seneca","Piper"],"3d9344":["DA42","Twin Star DA42","Diamond Aircraft"],"3d9a5a":["P68","P.68B Victor","Partenavia"],"3d9bd7":["PA34","Mewa PZL M-20","Pzl-mielec"],"3d99c0":["P68","P.68B Victor","Partenavia"],"3d9ac9":["DA42","Twin Star DA42","Diamond Aircraft"],"3d9e53":["MC10","Cri-Cri MC-15","Colomban"],"3d9137":["PA34","PA-34 200 Seneca","Piper"],"3d90e6":["PA34","PA-34 220T Seneca III","Piper"],"3d9f14":["DA42","Twin Star DA42","Diamond Aircraft"],"3d9086":["PA30","PA-30 160 Twin Comanche","Piper"],"3d9353":["PA34","PA-34 220T Seneca V","Piper"],"3d9c62":["P68","P.68C Victor","Vulcanair"],"3d9c37":["PA34","PA-34 220T Seneca IV","Piper"],"3d9cb6":["PA30","PA-30 160 Twin Comanche C","Piper"],"3d9a6f":["GA7","GA-7 Cougar","Grumman American"],"3d927a":["PA44","Piper PA-44 180T Turbo Seminole","Piper"],"3d9b3f":["PA34","",""],"3d9343":["DA42","Twin Star DA42","Diamond Aircraft"],"3d9810":["P68","P.68","Partenavia"],"3d99a6":["P68","P.68B Victor","Partenavia"],"3d9924":["PA34","PA-34 220T Seneca III","Piper"],"3d9c3a":["ZZZZ","Mini Twin","Carbotec"],"3d9a55":["P68","P.68B Victor","Partenavia"],"3d9130":["DA42","Diamond Aircraft Twin Star DA42","Diamond Aircraft"],"3d91f6":["PA30","PA-30 160 Twin Comanche B","Piper"],"3d9831":["PA34","PA-34 200T Seneca II","Piper"],"3d909e":["PA44","PA-44 180T Turbo Seminole","Piper"],"3d957d":["PA34","PA-34 220T Seneca IV","Piper"],"3d9379":["PA34","PA-34 200T Seneca II","Piper"],"3d9268":["P68","P.68B Victor","Partenavia"],"3d99c1":["P68","P.68B Victor","Partenavia"],"3d94ad":["DA42","Twin Star DA42","Diamond Aircraft"],"3d9a54":["PA34","PA-34 220T Seneca V","Piper"],"3d9fa3":["PA34","",""],"3d9bcf":["PA34","Piper PA-34 220T Seneca IV","Piper"],"3d9fd1":["PA34","PA-34 220T Seneca III","Piper"],"3d99b7":["DA42","Twin Star DA42","Diamond Aircraft"],"3d9fea":["DA42","Twin Star DA42","Diamond Aircraft"],"3d9f9d":["PA34","PA-34 220T Seneca III","Piper"],"3d975d":["DA42","Twin Star DA42","Diamond Aircraft"],"3d9ba6":["DA42","Twin Star DA42","Diamond Aircraft"],"3d9c16":["PA34","PA-34 200 Seneca","Piper"],"3d9be3":["PA44","PA-44 180 Seminole","Piper"],"3d9e72":["PA23","PA-23 Apache 160","Piper"]}